CHANGES.rst
LICENSE.txt
MANIFEST.in
README.rst
distribute_setup.py
setup.py
pypack/__init__.py
pypack/commands.py
pypack/templates/changes.txt
pypack/templates/distribute_setup.py
pypack/templates/empty.txt
pypack/templates/license.txt
pypack/templates/manifest.txt
pypack/templates/readme.txt
pypack/templates/setup.txt
pypack/templates/licenses/bsdnew.txt
pypack/templates/licenses/bsdsimple.txt
pypack/templates/licenses/gpl3.txt
pypack/templates/licenses/mit.txt
python_package_template.egg-info/PKG-INFO
python_package_template.egg-info/SOURCES.txt
python_package_template.egg-info/dependency_links.txt
python_package_template.egg-info/entry_points.txt
python_package_template.egg-info/top_level.txt