Metadata-Version: 1.0
Name: python-package-template
Version: 0.8.1
Summary: Provides a command to easily create a standard Python package layout (i.e. package directory, README file, setup.py, etc.).
Home-page: http://pypi.python.org/pypi/python-package-template/
Author: Gary Wilson Jr.
Author-email: gary.wilson@gmail.com
License: MIT
Platform: UNKNOWN
